bdpn/__init__.py
bdpn/bd_model.py
bdpn/bdmult_model.py
bdpn/bdmult_model2.py
bdpn/bdpn_model.py
bdpn/formulas.py
bdpn/model_distinguisher.py
bdpn/mtbd.py
bdpn/parameter_estimator.py
bdpn/tree_manager.py
bdpn-0.1.15.dist-info/LICENSE
bdpn-0.1.15.dist-info/METADATA
bdpn-0.1.15.dist-info/WHEEL
bdpn-0.1.15.dist-info/entry_points.txt
bdpn-0.1.15.dist-info/top_level.txt
bdpn-0.1.15.dist-info/RECORD
