Metadata-Version: 2.1
Name: bdpn
Version: 0.1.15
Summary: Estimation of BDPN parameters from phylogenetic trees.
Home-page: https://github.com/evolbioinfo/bdpn
Author: Anna Zhukova
Author-email: anna.zhukova@pasteur.fr
Keywords: phylogenetics,birth-death model,partner notification
Classifier: Development Status :: 4 - Beta
Classifier: Environment :: Console
Classifier: Intended Audience :: Developers
Classifier: Topic :: Scientific/Engineering :: Bio-Informatics
Classifier: Topic :: Software Development
Classifier: Topic :: Software Development :: Libraries :: Python Modules
License-File: LICENSE
Requires-Dist: six
Requires-Dist: ete3
Requires-Dist: numpy
Requires-Dist: scipy (==1.10.0-rc1)
Requires-Dist: biopython
